parse_to_syncano
