Metadata-Version: 1.1
Name: parse2syncano
Version: 0.0.4
Summary: A tool to migrate data from Parse to Syncano
Home-page: http://syncano.com
Author: Sebastian Opałczyński
Author-email: sebastian.opalczynski@syncano.com
License: UNKNOWN
Platform: UNKNOWN
Classifier: Development Status :: 3 - Alpha
Classifier: License :: OSI Approved :: MIT License
Classifier: Programming Language :: Python
Classifier: Programming Language :: Python :: 2.7
